{"title": "Edgy Catboy", "id": "EdgyCatboy", "stickers": [{"body": "0", "url": "mxc://matrix.org/zJroWBWSwvhukEVnyfwVfENg", "info": {"w": 256, "h": 256, "size": 85132, "mimetype": "image/png", "thumbnail_url": "mxc://matrix.org/zJroWBWSwvhukEVnyfwVfENg", "thumbnail_info": {"w": 256, "h": 256, "size": 85132, "mimetype": "image/png"}}, "msgtype": "m.sticker", "id": "sha256:6f50bc9aa653ae896775b5a9694531efba17056343a9c490c2332e1410f8c188"}, {"body": "1", "url": "mxc://matrix.org/LGTBJjgvyMGyhhYgzKGVPjjF", "info": {"w": 256, "h": 256, "size": 84020, "mimetype": "image/png", "thumbnail_url": "mxc://matrix.org/LGTBJjgvyMGyhhYgzKGVPjjF", "thumbnail_info": {"w": 256, "h": 256, "size": 84020, "mimetype": "image/png"}}, "msgtype": "m.sticker", "id": "sha256:6311d4fbd502f1cd2b8b90c709ab55feb21e409f4ba054f2642ca2c3892fa325"}, {"body": "10", "url": "mxc://matrix.org/oGbzXcXZKRpnmKnGpCAtoPkl", "info": {"w": 256, "h": 256, "size": 133297, "mimetype": "image/png", "thumbnail_url": "mxc://matrix.org/oGbzXcXZKRpnmKnGpCAtoPkl", "thumbnail_info": {"w": 256, "h": 256, "size": 133297, "mimetype": "image/png"}}, "msgtype": "m.sticker", "id": "sha256:fddb7d1b3516ea96dc06d5fa38e38d97782fb97a4a050c78ddb7f7da08c01b1e"}, {"body": "11", "url": "mxc://matrix.org/IlVjrjuvbsYXrvhffXnNiAFZ", "info": {"w": 256, "h": 256, "size": 68346, "mimetype": "image/png", "thumbnail_url": "mxc://matrix.org/IlVjrjuvbsYXrvhffXnNiAFZ", "thumbnail_info": {"w": 256, "h": 256, "size": 68346, "mimetype": "image/png"}}, "msgtype": "m.sticker", "id": "sha256:90ae4bf39ddbf1f6152c7390d7ed0123d28b956d7fabb3f549293566d740cbc2"}, {"body": "12", "url": "mxc://matrix.org/VavpDHGxbFTmrUJFUollquhz", "info": {"w": 256, "h": 256, "size": 114469, "mimetype": "image/png", "thumbnail_url": "mxc://matrix.org/VavpDHGxbFTmrUJFUollquhz", "thumbnail_info": {"w": 256, "h": 256, "size": 114469, "mimetype": "image/png"}}, "msgtype": "m.sticker", "id": "sha256:d208be9f1f3777ca50900e696936e7b1de1affb3eed2d170123b038b6cf17969"}, {"body": "13", "url": "mxc://matrix.org/JqJzarxgYGOWfFsyJbWakUrQ", "info": {"w": 256, "h": 256, "size": 80528, "mimetype": "image/png", "thumbnail_url": "mxc://matrix.org/JqJzarxgYGOWfFsyJbWakUrQ", "thumbnail_info": {"w": 256, "h": 256, "size": 80528, "mimetype": "image/png"}}, "msgtype": "m.sticker", "id": "sha256:f66adea661c359a54cf8368beaeecf9e4e175ceb7e6e316b6e75a6c642e31e53"}, {"body": "14", "url": "mxc://matrix.org/IHjGYPkeNzsXDYMFIXKjErLG", "info": {"w": 256, "h": 256, "size": 94172, "mimetype": "image/png", "thumbnail_url": "mxc://matrix.org/IHjGYPkeNzsXDYMFIXKjErLG", "thumbnail_info": {"w": 256, "h": 256, "size": 94172, "mimetype": "image/png"}}, "msgtype": "m.sticker", "id": "sha256:038db898411e849bd700d6d58317e7b5263fe2fce83b703508c142e21b76462a"}, {"body": "15", "url": "mxc://matrix.org/IXypowiYVXLfrfHXBnylNIBb", "info": {"w": 256, "h": 256, "size": 75789, "mimetype": "image/png", "thumbnail_url": "mxc://matrix.org/IXypowiYVXLfrfHXBnylNIBb", "thumbnail_info": {"w": 256, "h": 256, "size": 75789, "mimetype": "image/png"}}, "msgtype": "m.sticker", "id": "sha256:e93d0d2c8ba2116cb1b4e7fddd01f9cbb1c0dc382449cfcf42d0cc68260a716f"}, {"body": "16", "url": "mxc://matrix.org/QpCzVPSedMTLcyIWyXVdzyNx", "info": {"w": 256, "h": 256, "size": 106481, "mimetype": "image/png", "thumbnail_url": "mxc://matrix.org/QpCzVPSedMTLcyIWyXVdzyNx", "thumbnail_info": {"w": 256, "h": 256, "size": 106481, "mimetype": "image/png"}}, "msgtype": "m.sticker", "id": "sha256:f9d01803d7bb994c69b9a9287fac366308b9f024ebe3ebf845468b3c11583fa7"}, {"body": "17", "url": "mxc://matrix.org/hweBGdovDbnNCwazWXyRURtW", "info": {"w": 256, "h": 256, "size": 107293, "mimetype": "image/png", "thumbnail_url": "mxc://matrix.org/hweBGdovDbnNCwazWXyRURtW", "thumbnail_info": {"w": 256, "h": 256, "size": 107293, "mimetype": "image/png"}}, "msgtype": "m.sticker", "id": "sha256:f02b95855d1ad6f9637afb2869f161238d81ce59c6c7ba262124b05a3dc94a2f"}, {"body": "18", "url": "mxc://matrix.org/KVNBbZuWuttYRuLlLoGVpiLu", "info": {"w": 256, "h": 256, "size": 78075, "mimetype": "image/png", "thumbnail_url": "mxc://matrix.org/KVNBbZuWuttYRuLlLoGVpiLu", "thumbnail_info": {"w": 256, "h": 256, "size": 78075, "mimetype": "image/png"}}, "msgtype": "m.sticker", "id": "sha256:77716031c262857bfb6de369b29d91627c5ea026d70dcb0ebf37915c139289d0"}, {"body": "19", "url": "mxc://matrix.org/HbtCFNHbZVKcWRXPikSkYTfy", "info": {"w": 256, "h": 256, "size": 104608, "mimetype": "image/png", "thumbnail_url": "mxc://matrix.org/HbtCFNHbZVKcWRXPikSkYTfy", "thumbnail_info": {"w": 256, "h": 256, "size": 104608, "mimetype": "image/png"}}, "msgtype": "m.sticker", "id": "sha256:541d7167a3a3dc1e4f6dedd1e0ae83837309bded031b11bd3f732aec639e18d1"}, {"body": "2", "url": "mxc://matrix.org/qlMAPAGtiZigcKLbrOgwsVhY", "info": {"w": 256, "h": 256, "size": 79198, "mimetype": "image/png", "thumbnail_url": "mxc://matrix.org/qlMAPAGtiZigcKLbrOgwsVhY", "thumbnail_info": {"w": 256, "h": 256, "size": 79198, "mimetype": "image/png"}}, "msgtype": "m.sticker", "id": "sha256:a81091c70e32873ee07c3721a62b202d8b5010dfc2151ad6f2db86d9a2f93f85"}, {"body": "20", "url": "mxc://matrix.org/LnQnXMcyrXDOibEONwlocrce", "info": {"w": 256, "h": 256, "size": 81147, "mimetype": "image/png", "thumbnail_url": "mxc://matrix.org/LnQnXMcyrXDOibEONwlocrce", "thumbnail_info": {"w": 256, "h": 256, "size": 81147, "mimetype": "image/png"}}, "msgtype": "m.sticker", "id": "sha256:a64f1b225c8ba2a3440a0ba462b0abae43cac85177cbfde61f70d9db91c696ad"}, {"body": "21", "url": "mxc://matrix.org/EkJoAKKFQXRFmicrxXUslbRu", "info": {"w": 256, "h": 256, "size": 128352, "mimetype": "image/png", "thumbnail_url": "mxc://matrix.org/EkJoAKKFQXRFmicrxXUslbRu", "thumbnail_info": {"w": 256, "h": 256, "size": 128352, "mimetype": "image/png"}}, "msgtype": "m.sticker", "id": "sha256:a9ba64ad3d06751ab86a9addf181fd9357001ec9a126c9c804d36153bd80adb0"}, {"body": "22", "url": "mxc://matrix.org/ZbDxciyeaMOVLgLLMnuCjcUo", "info": {"w": 256, "h": 256, "size": 109150, "mimetype": "image/png", "thumbnail_url": "mxc://matrix.org/ZbDxciyeaMOVLgLLMnuCjcUo", "thumbnail_info": {"w": 256, "h": 256, "size": 109150, "mimetype": "image/png"}}, "msgtype": "m.sticker", "id": "sha256:7569a608a1af67aeb5875ce40b8ca118678e6172d55daf6997067cafe98bac9a"}, {"body": "23", "url": "mxc://matrix.org/xfqcAwCWYzKAmdkjKfKYlkUc", "info": {"w": 256, "h": 256, "size": 83650, "mimetype": "image/png", "thumbnail_url": "mxc://matrix.org/xfqcAwCWYzKAmdkjKfKYlkUc", "thumbnail_info": {"w": 256, "h": 256, "size": 83650, "mimetype": "image/png"}}, "msgtype": "m.sticker", "id": "sha256:1c09994f2b5e3a55093e31c1d78dd8db8b321e8624142505d113117c3c444621"}, {"body": "24", "url": "mxc://matrix.org/qgZwAULDIzZpdIchNSvjyDKG", "info": {"w": 256, "h": 256, "size": 95207, "mimetype": "image/png", "thumbnail_url": "mxc://matrix.org/qgZwAULDIzZpdIchNSvjyDKG", "thumbnail_info": {"w": 256, "h": 256, "size": 95207, "mimetype": "image/png"}}, "msgtype": "m.sticker", "id": "sha256:4b2a827591b6b0977fdb09d9b1135459a8e6ced70afaa49cfe67237e6b33b3eb"}, {"body": "25", "url": "mxc://matrix.org/zTTnMzTQmDXOcolzuGPRhQzu", "info": {"w": 256, "h": 256, "size": 92963, "mimetype": "image/png", "thumbnail_url": "mxc://matrix.org/zTTnMzTQmDXOcolzuGPRhQzu", "thumbnail_info": {"w": 256, "h": 256, "size": 92963, "mimetype": "image/png"}}, "msgtype": "m.sticker", "id": "sha256:689cab8ea3a58a984008427fe7a75cfef01624b11147326a1549276d7f7f715e"}, {"body": "26", "url": "mxc://matrix.org/PoPeyrFngwlwniagoaVzwUEL", "info": {"w": 256, "h": 256, "size": 83273, "mimetype": "image/png", "thumbnail_url": "mxc://matrix.org/PoPeyrFngwlwniagoaVzwUEL", "thumbnail_info": {"w": 256, "h": 256, "size": 83273, "mimetype": "image/png"}}, "msgtype": "m.sticker", "id": "sha256:69b39acab7724ff759794324efbfd3664c09ee189428648a5009af3c74d9840e"}, {"body": "27", "url": "mxc://matrix.org/DtDMnsroCCrSQCmmHazRIcDI", "info": {"w": 256, "h": 256, "size": 61998, "mimetype": "image/png", "thumbnail_url": "mxc://matrix.org/DtDMnsroCCrSQCmmHazRIcDI", "thumbnail_info": {"w": 256, "h": 256, "size": 61998, "mimetype": "image/png"}}, "msgtype": "m.sticker", "id": "sha256:6fcfa00fe24b5b880ff95347114b78fa4a6e2ba0ae082b4695ea3f146624900b"}, {"body": "28", "url": "mxc://matrix.org/PEAiUkJkdujXhvJKVdIMcyhy", "info": {"w": 256, "h": 256, "size": 172465, "mimetype": "image/png", "thumbnail_url": "mxc://matrix.org/PEAiUkJkdujXhvJKVdIMcyhy", "thumbnail_info": {"w": 256, "h": 256, "size": 172465, "mimetype": "image/png"}}, "msgtype": "m.sticker", "id": "sha256:e63783b7fde753ece86d84a1e53874a8e7adbef33a8d1340be8172cb33aefff2"}, {"body": "29", "url": "mxc://matrix.org/XtNnYYdGIWPDDCsSjipDMWlt", "info": {"w": 256, "h": 256, "size": 70716, "mimetype": "image/png", "thumbnail_url": "mxc://matrix.org/XtNnYYdGIWPDDCsSjipDMWlt", "thumbnail_info": {"w": 256, "h": 256, "size": 70716, "mimetype": "image/png"}}, "msgtype": "m.sticker", "id": "sha256:017d5d80ed193841afdf21aaca9b96939b5790bd2a691e1fb33d72ebde2963b1"}, {"body": "3", "url": "mxc://matrix.org/uKthcpWlTZPaPjJlRJlfvgPo", "info": {"w": 256, "h": 256, "size": 110308, "mimetype": "image/png", "thumbnail_url": "mxc://matrix.org/uKthcpWlTZPaPjJlRJlfvgPo", "thumbnail_info": {"w": 256, "h": 256, "size": 110308, "mimetype": "image/png"}}, "msgtype": "m.sticker", "id": "sha256:213dcb241d58d4b1ff8f64b2ebba4298430980179015771728206d358b89832e"}, {"body": "30", "url": "mxc://matrix.org/jVqmKEXuhThiJHODEsmqvjqq", "info": {"w": 256, "h": 256, "size": 93494, "mimetype": "image/png", "thumbnail_url": "mxc://matrix.org/jVqmKEXuhThiJHODEsmqvjqq", "thumbnail_info": {"w": 256, "h": 256, "size": 93494, "mimetype": "image/png"}}, "msgtype": "m.sticker", "id": "sha256:9e2d249e0c92b5c79e25344613eca38f2956569d68a468d151a5b1eb41a5c439"}, {"body": "31", "url": "mxc://matrix.org/OoatCkqCobnStQcUKBKAEgHs", "info": {"w": 256, "h": 256, "size": 78319, "mimetype": "image/png", "thumbnail_url": "mxc://matrix.org/OoatCkqCobnStQcUKBKAEgHs", "thumbnail_info": {"w": 256, "h": 256, "size": 78319, "mimetype": "image/png"}}, "msgtype": "m.sticker", "id": "sha256:039dda23096a4a2793cf41d35ee036c3c7dd083fa4ea259e21cf880a22728dab"}, {"body": "32", "url": "mxc://matrix.org/kFLWZbMUzYSrEIUNnijYsbZk", "info": {"w": 256, "h": 256, "size": 77084, "mimetype": "image/png", "thumbnail_url": "mxc://matrix.org/kFLWZbMUzYSrEIUNnijYsbZk", "thumbnail_info": {"w": 256, "h": 256, "size": 77084, "mimetype": "image/png"}}, "msgtype": "m.sticker", "id": "sha256:0e8f3712f4e5b41822e49f19611c759120b2a0fbb9ac449a7c9073ce2b783f33"}, {"body": "33", "url": "mxc://matrix.org/XKIzCikSuoGYMYTcEQNFyDRe", "info": {"w": 256, "h": 256, "size": 78060, "mimetype": "image/png", "thumbnail_url": "mxc://matrix.org/XKIzCikSuoGYMYTcEQNFyDRe", "thumbnail_info": {"w": 256, "h": 256, "size": 78060, "mimetype": "image/png"}}, "msgtype": "m.sticker", "id": "sha256:e853c780f3b401d83652a90c403d23b0c9b2012f045ad53879d1643d4114a08d"}, {"body": "34", "url": "mxc://matrix.org/rBhXXTiVhYSpSredOdxJzOQf", "info": {"w": 256, "h": 256, "size": 113138, "mimetype": "image/png", "thumbnail_url": "mxc://matrix.org/rBhXXTiVhYSpSredOdxJzOQf", "thumbnail_info": {"w": 256, "h": 256, "size": 113138, "mimetype": "image/png"}}, "msgtype": "m.sticker", "id": "sha256:e2e17cd5e129cdaa51091de2d179dad4e78e073ff5d4738370066c5b6201662f"}, {"body": "35", "url": "mxc://matrix.org/kwqqodqEvNmMFziuhdOGTjxa", "info": {"w": 256, "h": 256, "size": 76610, "mimetype": "image/png", "thumbnail_url": "mxc://matrix.org/kwqqodqEvNmMFziuhdOGTjxa", "thumbnail_info": {"w": 256, "h": 256, "size": 76610, "mimetype": "image/png"}}, "msgtype": "m.sticker", "id": "sha256:a01ec2bebc928ac7b342c557a84b15e03f3df08067c9c5caf152efd53714dc5a"}, {"body": "36", "url": "mxc://matrix.org/IZJjSyMWKrGkmaSsuzOtAyPf", "info": {"w": 256, "h": 256, "size": 104839, "mimetype": "image/png", "thumbnail_url": "mxc://matrix.org/IZJjSyMWKrGkmaSsuzOtAyPf", "thumbnail_info": {"w": 256, "h": 256, "size": 104839, "mimetype": "image/png"}}, "msgtype": "m.sticker", "id": "sha256:7e82ed5ceaaf12fd715712098e35b705525adfcfd8a7e920ab341a8f0f387cdf"}, {"body": "37", "url": "mxc://matrix.org/KNFkmenhLoHnjZaqnzinLEms", "info": {"w": 256, "h": 256, "size": 94245, "mimetype": "image/png", "thumbnail_url": "mxc://matrix.org/KNFkmenhLoHnjZaqnzinLEms", "thumbnail_info": {"w": 256, "h": 256, "size": 94245, "mimetype": "image/png"}}, "msgtype": "m.sticker", "id": "sha256:c1d18d9472e10aea14e3f8057e2b76392ae2d0bb1f9ed23db51809ced94ca525"}, {"body": "38", "url": "mxc://matrix.org/svcSxsyXBjFUjihAbBGypZfE", "info": {"w": 256, "h": 256, "size": 78191, "mimetype": "image/png", "thumbnail_url": "mxc://matrix.org/svcSxsyXBjFUjihAbBGypZfE", "thumbnail_info": {"w": 256, "h": 256, "size": 78191, "mimetype": "image/png"}}, "msgtype": "m.sticker", "id": "sha256:c93a955d63cebb19e62d184455d63903af4276f9a8d686ee0354ab9333f2df34"}, {"body": "39", "url": "mxc://matrix.org/RqKvwJCqEuYUuvfIioWLxmrh", "info": {"w": 256, "h": 256, "size": 81164, "mimetype": "image/png", "thumbnail_url": "mxc://matrix.org/RqKvwJCqEuYUuvfIioWLxmrh", "thumbnail_info": {"w": 256, "h": 256, "size": 81164, "mimetype": "image/png"}}, "msgtype": "m.sticker", "id": "sha256:48fe9bab0121e9080adc0ebcbc0e448316c3bb5eeaad6ba2e4c792910e2df438"}, {"body": "4", "url": "mxc://matrix.org/QjTSyjUUmXaFgTMaHqpJrPjJ", "info": {"w": 256, "h": 256, "size": 82201, "mimetype": "image/png", "thumbnail_url": "mxc://matrix.org/QjTSyjUUmXaFgTMaHqpJrPjJ", "thumbnail_info": {"w": 256, "h": 256, "size": 82201, "mimetype": "image/png"}}, "msgtype": "m.sticker", "id": "sha256:d820b69977308bff367bb6ad981c47ba26d82af388ca2aa2fa5427bfc6f948d7"}, {"body": "40", "url": "mxc://matrix.org/XUgRzvBWWpBpGEkwlctylEPa", "info": {"w": 256, "h": 256, "size": 72178, "mimetype": "image/png", "thumbnail_url": "mxc://matrix.org/XUgRzvBWWpBpGEkwlctylEPa", "thumbnail_info": {"w": 256, "h": 256, "size": 72178, "mimetype": "image/png"}}, "msgtype": "m.sticker", "id": "sha256:fe06046496d5e07a31867310205dbb4bcbac997c3eb63d38846b47650fe182e2"}, {"body": "41", "url": "mxc://matrix.org/scWMhaRQHEtTbEteZoWkGlRk", "info": {"w": 256, "h": 256, "size": 115956, "mimetype": "image/png", "thumbnail_url": "mxc://matrix.org/scWMhaRQHEtTbEteZoWkGlRk", "thumbnail_info": {"w": 256, "h": 256, "size": 115956, "mimetype": "image/png"}}, "msgtype": "m.sticker", "id": "sha256:91298aeb80d9a5eaaf882edee11d60c1c66570faed72edef15536582b6bfeaea"}, {"body": "42", "url": "mxc://matrix.org/iFcqrZqglagVHyIfSOKqEsax", "info": {"w": 256, "h": 256, "size": 65793, "mimetype": "image/png", "thumbnail_url": "mxc://matrix.org/iFcqrZqglagVHyIfSOKqEsax", "thumbnail_info": {"w": 256, "h": 256, "size": 65793, "mimetype": "image/png"}}, "msgtype": "m.sticker", "id": "sha256:9c0ef049927af6912ee1f3f1e4507a0032ff9f195d8737728154643b751d0533"}, {"body": "43", "url": "mxc://matrix.org/zlgbmUBQasFrMaYyqwvUEQWP", "info": {"w": 256, "h": 256, "size": 75955, "mimetype": "image/png", "thumbnail_url": "mxc://matrix.org/zlgbmUBQasFrMaYyqwvUEQWP", "thumbnail_info": {"w": 256, "h": 256, "size": 75955, "mimetype": "image/png"}}, "msgtype": "m.sticker", "id": "sha256:81a3bfcd3c2d64cf9967eee171167a731678adfc1df1ab81fd8a0cfd29807231"}, {"body": "44", "url": "mxc://matrix.org/SwAHKfRolgZxSPKACihQOKXw", "info": {"w": 256, "h": 256, "size": 74537, "mimetype": "image/png", "thumbnail_url": "mxc://matrix.org/SwAHKfRolgZxSPKACihQOKXw", "thumbnail_info": {"w": 256, "h": 256, "size": 74537, "mimetype": "image/png"}}, "msgtype": "m.sticker", "id": "sha256:9a0dd581765d1472fcf13e6eeea51465881023418ca5ae11537d71fd4b465e7d"}, {"body": "45", "url": "mxc://matrix.org/nSutqOVnsbuvSGSXYfIQsIJF", "info": {"w": 256, "h": 256, "size": 92091, "mimetype": "image/png", "thumbnail_url": "mxc://matrix.org/nSutqOVnsbuvSGSXYfIQsIJF", "thumbnail_info": {"w": 256, "h": 256, "size": 92091, "mimetype": "image/png"}}, "msgtype": "m.sticker", "id": "sha256:383eddc4d0103a5225a27901bbe1591139e4319edfb35e9ab6c3966a4d507e54"}, {"body": "46", "url": "mxc://matrix.org/JjhdzuncPVHTKnHlkIaUnQbr", "info": {"w": 256, "h": 256, "size": 106800, "mimetype": "image/png", "thumbnail_url": "mxc://matrix.org/JjhdzuncPVHTKnHlkIaUnQbr", "thumbnail_info": {"w": 256, "h": 256, "size": 106800, "mimetype": "image/png"}}, "msgtype": "m.sticker", "id": "sha256:36a23871463d3cb56e50ab784951b2c7803b76a6288e96065d257a33baf6fce2"}, {"body": "47", "url": "mxc://matrix.org/EIcRzLltpMZpSFnFJUDZUSSv", "info": {"w": 256, "h": 256, "size": 111591, "mimetype": "image/png", "thumbnail_url": "mxc://matrix.org/EIcRzLltpMZpSFnFJUDZUSSv", "thumbnail_info": {"w": 256, "h": 256, "size": 111591, "mimetype": "image/png"}}, "msgtype": "m.sticker", "id": "sha256:422a3a2502295d1b04bab2a305400c3ef54d18c498a5e2dfeb0f8913344a1646"}, {"body": "48", "url": "mxc://matrix.org/vzrBAxGskCEruDIsqNugwMDg", "info": {"w": 256, "h": 256, "size": 109877, "mimetype": "image/png", "thumbnail_url": "mxc://matrix.org/vzrBAxGskCEruDIsqNugwMDg", "thumbnail_info": {"w": 256, "h": 256, "size": 109877, "mimetype": "image/png"}}, "msgtype": "m.sticker", "id": "sha256:047d03f303ba02e302c48569cf322bc0687a4ae950cbfd768a6d7f4669102d73"}, {"body": "49", "url": "mxc://matrix.org/gbrXmGpRSdGtwmkhcnbVsBgn", "info": {"w": 256, "h": 256, "size": 83127, "mimetype": "image/png", "thumbnail_url": "mxc://matrix.org/gbrXmGpRSdGtwmkhcnbVsBgn", "thumbnail_info": {"w": 256, "h": 256, "size": 83127, "mimetype": "image/png"}}, "msgtype": "m.sticker", "id": "sha256:5efe34f822de415a926701c52501368e7b24dbf491e4134726e374bb6b9914db"}, {"body": "5", "url": "mxc://matrix.org/mLRQAZEQlehVSCwUXDaYSxbJ", "info": {"w": 256, "h": 256, "size": 68402, "mimetype": "image/png", "thumbnail_url": "mxc://matrix.org/mLRQAZEQlehVSCwUXDaYSxbJ", "thumbnail_info": {"w": 256, "h": 256, "size": 68402, "mimetype": "image/png"}}, "msgtype": "m.sticker", "id": "sha256:a1bbdb9adf572efc1748b08fdd6835e79f3ff2fe26de8f7ca6e938721d3be2e1"}, {"body": "50", "url": "mxc://matrix.org/UcojCFFQefqXnnAgZQMvSdwX", "info": {"w": 256, "h": 256, "size": 123206, "mimetype": "image/png", "thumbnail_url": "mxc://matrix.org/UcojCFFQefqXnnAgZQMvSdwX", "thumbnail_info": {"w": 256, "h": 256, "size": 123206, "mimetype": "image/png"}}, "msgtype": "m.sticker", "id": "sha256:126444f7d45f3d458bc5a597e69610b24066dc55ca525517807e070edfcdfd3d"}, {"body": "51", "url": "mxc://matrix.org/XhcjZzuyiFVahsvQLZPWxUSU", "info": {"w": 256, "h": 256, "size": 79288, "mimetype": "image/png", "thumbnail_url": "mxc://matrix.org/XhcjZzuyiFVahsvQLZPWxUSU", "thumbnail_info": {"w": 256, "h": 256, "size": 79288, "mimetype": "image/png"}}, "msgtype": "m.sticker", "id": "sha256:a46ec6fc8deb4facd2276d526a9005671d530158d4fb23662a67b2d7d42efc75"}, {"body": "52", "url": "mxc://matrix.org/YtkbsgJuEbeatuMrgwtagmUD", "info": {"w": 256, "h": 256, "size": 175523, "mimetype": "image/png", "thumbnail_url": "mxc://matrix.org/YtkbsgJuEbeatuMrgwtagmUD", "thumbnail_info": {"w": 256, "h": 256, "size": 175523, "mimetype": "image/png"}}, "msgtype": "m.sticker", "id": "sha256:eb47a33f01856219ac9ef646f6573b96b0d647bbb0f1c82ede1b160fa23e1e64"}, {"body": "53", "url": "mxc://matrix.org/QciAbkSHVWiUmGgmDmtzwOyc", "info": {"w": 256, "h": 256, "size": 99472, "mimetype": "image/png", "thumbnail_url": "mxc://matrix.org/QciAbkSHVWiUmGgmDmtzwOyc", "thumbnail_info": {"w": 256, "h": 256, "size": 99472, "mimetype": "image/png"}}, "msgtype": "m.sticker", "id": "sha256:f57f085ada08d6c2770b1e616a0bdb233ffed04e99d9a0a45ea476d66fd8649c"}, {"body": "54", "url": "mxc://matrix.org/VoKhKYEgWTuhtCfXjZShCZad", "info": {"w": 256, "h": 256, "size": 74015, "mimetype": "image/png", "thumbnail_url": "mxc://matrix.org/VoKhKYEgWTuhtCfXjZShCZad", "thumbnail_info": {"w": 256, "h": 256, "size": 74015, "mimetype": "image/png"}}, "msgtype": "m.sticker", "id": "sha256:fa644f70be1775f979fe612fe91da2e13220a072e939a5ccee4e49623f49c63a"}, {"body": "55", "url": "mxc://matrix.org/JPhekXMvlbFWwRYhiFiuTTkv", "info": {"w": 256, "h": 256, "size": 103797, "mimetype": "image/png", "thumbnail_url": "mxc://matrix.org/JPhekXMvlbFWwRYhiFiuTTkv", "thumbnail_info": {"w": 256, "h": 256, "size": 103797, "mimetype": "image/png"}}, "msgtype": "m.sticker", "id": "sha256:a098b4bc7287375f247fab8f7be93b99a45230da7db93a90bc247cdbd02104f8"}, {"body": "56", "url": "mxc://matrix.org/vQEYEcpOQLwiLWJyzOATDqyb", "info": {"w": 256, "h": 256, "size": 90058, "mimetype": "image/png", "thumbnail_url": "mxc://matrix.org/vQEYEcpOQLwiLWJyzOATDqyb", "thumbnail_info": {"w": 256, "h": 256, "size": 90058, "mimetype": "image/png"}}, "msgtype": "m.sticker", "id": "sha256:cedf32f67659b88568f15bd3ed9a9f3db7ee98aae7aae721407a3f532356bfba"}, {"body": "57", "url": "mxc://matrix.org/mlnHfRTKELyCKNkdizmVkjpR", "info": {"w": 256, "h": 256, "size": 87608, "mimetype": "image/png", "thumbnail_url": "mxc://matrix.org/mlnHfRTKELyCKNkdizmVkjpR", "thumbnail_info": {"w": 256, "h": 256, "size": 87608, "mimetype": "image/png"}}, "msgtype": "m.sticker", "id": "sha256:45278ffc89d18d8cf9cbee69f50781efbd025cb2db8af606eff5c313dfdf3a0d"}, {"body": "58", "url": "mxc://matrix.org/USEVGWnteBKcHlNAMqGRBjBR", "info": {"w": 256, "h": 256, "size": 53430, "mimetype": "image/png", "thumbnail_url": "mxc://matrix.org/USEVGWnteBKcHlNAMqGRBjBR", "thumbnail_info": {"w": 256, "h": 256, "size": 53430, "mimetype": "image/png"}}, "msgtype": "m.sticker", "id": "sha256:a561db2cf9883d8794a7593e39bf157b2e5d0377a964b2e0f547d74cfbe03fb1"}, {"body": "59", "url": "mxc://matrix.org/JdHTpSzAtAUuruhkGJWwyQlo", "info": {"w": 256, "h": 256, "size": 80355, "mimetype": "image/png", "thumbnail_url": "mxc://matrix.org/JdHTpSzAtAUuruhkGJWwyQlo", "thumbnail_info": {"w": 256, "h": 256, "size": 80355, "mimetype": "image/png"}}, "msgtype": "m.sticker", "id": "sha256:2bb487ad712c1fd66b3701cc1b3fd6e6295c15eeff9992e880fa767fb011a0fb"}, {"body": "6", "url": "mxc://matrix.org/asSugQRcMgGfSVzHXslJoRYz", "info": {"w": 256, "h": 256, "size": 131987, "mimetype": "image/png", "thumbnail_url": "mxc://matrix.org/asSugQRcMgGfSVzHXslJoRYz", "thumbnail_info": {"w": 256, "h": 256, "size": 131987, "mimetype": "image/png"}}, "msgtype": "m.sticker", "id": "sha256:631ace2e26c96e962aae981640f4ff3ccdf430595f9822da4e908ac58313a3a1"}, {"body": "60", "url": "mxc://matrix.org/KMzZHNSFXcBzBmqwHTiIaReW", "info": {"w": 256, "h": 256, "size": 128327, "mimetype": "image/png", "thumbnail_url": "mxc://matrix.org/KMzZHNSFXcBzBmqwHTiIaReW", "thumbnail_info": {"w": 256, "h": 256, "size": 128327, "mimetype": "image/png"}}, "msgtype": "m.sticker", "id": "sha256:8eed81e4056ce290e799b726f21f28071fbb4447dc42a9a240bf424d790f8ead"}, {"body": "61", "url": "mxc://matrix.org/hRFVxAFhUOZXOfzUXWUZfkFW", "info": {"w": 256, "h": 256, "size": 77885, "mimetype": "image/png", "thumbnail_url": "mxc://matrix.org/hRFVxAFhUOZXOfzUXWUZfkFW", "thumbnail_info": {"w": 256, "h": 256, "size": 77885, "mimetype": "image/png"}}, "msgtype": "m.sticker", "id": "sha256:5624760a6cb84a6a13109b2c6a92f74e7d92ca0f40a789882067a0790ce324fb"}, {"body": "62", "url": "mxc://matrix.org/ETjUBVmGZXITESaLEjuzzaNV", "info": {"w": 256, "h": 256, "size": 74517, "mimetype": "image/png", "thumbnail_url": "mxc://matrix.org/ETjUBVmGZXITESaLEjuzzaNV", "thumbnail_info": {"w": 256, "h": 256, "size": 74517, "mimetype": "image/png"}}, "msgtype": "m.sticker", "id": "sha256:d2743bc457200a8b08408b4876d7dcb7de1673decf5382602c310cabdfeeb247"}, {"body": "7", "url": "mxc://matrix.org/zymMetxfDRFPxUIUfFBPUitG", "info": {"w": 256, "h": 256, "size": 101402, "mimetype": "image/png", "thumbnail_url": "mxc://matrix.org/zymMetxfDRFPxUIUfFBPUitG", "thumbnail_info": {"w": 256, "h": 256, "size": 101402, "mimetype": "image/png"}}, "msgtype": "m.sticker", "id": "sha256:67df03932f62f44c37e8a0b56b62573f15bd45ae992339ca159b5506e618d41f"}, {"body": "8", "url": "mxc://matrix.org/rtcnkxRsanldSsbPCZixrEjx", "info": {"w": 256, "h": 256, "size": 89553, "mimetype": "image/png", "thumbnail_url": "mxc://matrix.org/rtcnkxRsanldSsbPCZixrEjx", "thumbnail_info": {"w": 256, "h": 256, "size": 89553, "mimetype": "image/png"}}, "msgtype": "m.sticker", "id": "sha256:14edf53f607ee4fb2515a834b2b12388fc3285e253f3584236dcb259889e196c"}, {"body": "9", "url": "mxc://matrix.org/ZtYdaPOuGXQqntxgczUBJGGl", "info": {"w": 256, "h": 256, "size": 98941, "mimetype": "image/png", "thumbnail_url": "mxc://matrix.org/ZtYdaPOuGXQqntxgczUBJGGl", "thumbnail_info": {"w": 256, "h": 256, "size": 98941, "mimetype": "image/png"}}, "msgtype": "m.sticker", "id": "sha256:17c092a7cd456d52b74f4e4aea3ced96d3c2665d200d4534758ca46bbb09f563"}]}